qtmodern/__init__.py
qtmodern/_utils.py
qtmodern/styles.py
qtmodern/windows.py
qtmodern/resources/frameless.qss
qtmodern/resources/style.qss
qtmodern-0.2.0.dist-info/LICENSE
qtmodern-0.2.0.dist-info/METADATA
qtmodern-0.2.0.dist-info/WHEEL
qtmodern-0.2.0.dist-info/top_level.txt
qtmodern-0.2.0.dist-info/RECORD
