Metadata-Version: 1.1
Name: qtmodern
Version: 0.2.0
Summary: Qt Widgets Modern User Interface
Home-page: https://www.github.com/gmarull/qtmodern
Author: Gerard Marull-Paretas
Author-email: gerardmarull@gmail.com
License: MIT
Platform: UNKNOWN
Classifier: Development Status :: 3 - Alpha
Classifier: Intended Audience :: Developers
Classifier: License :: OSI Approved :: MIT License
Classifier: Operating System :: OS Independent
Classifier: Programming Language :: Python
Classifier: Topic :: Software Development :: User Interfaces
